[
  {
    "id": 1,
    "subject": "Math",
    "question": "🍎 Rohan has 3 apples. His mother gave him 2 more. How many apples does he have now?",
    "option1": "4",
    "option2": "5",
    "option3": "6",
    "option4": "7",
    "answer": "5",
    "level": 1
  },
  {
    "id": 2,
    "subject": "Math",
    "question": "🐦 There are 8 birds on a tree. 3 birds fly away. How many birds are left?",
    "option1": "4",
    "option2": "6",
    "option3": "5",
    "option4": "3",
    "answer": "5",
    "level": 1
  },
  {
    "id": 3,
    "subject": "Math",
    "question": "⭐ Which number comes AFTER 9?",
    "option1": "8",
    "option2": "11",
    "option3": "10",
    "option4": "7",
    "answer": "10",
    "level": 1
  },
  {
    "id": 4,
    "subject": "Math",
    "question": "🔢 Which is the BIGGEST number?",
    "option1": "15",
    "option2": "9",
    "option3": "20",
    "option4": "11",
    "answer": "20",
    "level": 2
  },
  {
    "id": 5,
    "subject": "Math",
    "question": "🍬 Priya has 2 chocolates. Her friend gives her 2 more. How many does she have in all?",
    "option1": "2",
    "option2": "3",
    "option3": "5",
    "option4": "4",
    "answer": "4",
    "level": 2
  }
]
